zope/testrunner/__init__.py
zope/testrunner/__main__.py
zope/testrunner/_doctest.py
zope/testrunner/coverage.py
zope/testrunner/debug.py
zope/testrunner/digraph.py
zope/testrunner/exceptions.py
zope/testrunner/feature.py
zope/testrunner/filter.py
zope/testrunner/find.py
zope/testrunner/formatter.py
zope/testrunner/garbagecollection.py
zope/testrunner/interfaces.py
zope/testrunner/layer.py
zope/testrunner/listing.py
zope/testrunner/logsupport.py
zope/testrunner/options.py
zope/testrunner/process.py
zope/testrunner/profiling.py
zope/testrunner/refcount.py
zope/testrunner/runner.py
zope/testrunner/selftest.py
zope/testrunner/shuffle.py
zope/testrunner/statistics.py
zope/testrunner/tb_format.py
zope/testrunner/threadsupport.py
zope/testrunner/util.py
zope/testrunner/tests/__init__.py
zope/testrunner/tests/test_digraph.py
zope/testrunner/tests/test_doctest.py
zope/testrunner/tests/test_filter.py
zope/testrunner/tests/test_find.py
zope/testrunner/tests/test_logsupport.py
zope/testrunner/tests/test_runner.py
zope/testrunner/tests/test_subunit.py
zope/testrunner/tests/test_threadsupport.py
zope/testrunner/tests/test_xml_output.py
zope/testrunner/tests/testrunner-arguments.rst
zope/testrunner/tests/testrunner-colors.rst
zope/testrunner/tests/testrunner-coverage-win32.rst
zope/testrunner/tests/testrunner-coverage.rst
zope/testrunner/tests/testrunner-debugging-import-failure.rst
zope/testrunner/tests/testrunner-debugging-layer-setup.rst
zope/testrunner/tests/testrunner-debugging-nonprintable-exc.rst
zope/testrunner/tests/testrunner-debugging.rst
zope/testrunner/tests/testrunner-discovery.rst
zope/testrunner/tests/testrunner-edge-cases.rst
zope/testrunner/tests/testrunner-errors.rst
zope/testrunner/tests/testrunner-expected-failures.rst
zope/testrunner/tests/testrunner-gc-after-test.rst
zope/testrunner/tests/testrunner-gc.rst
zope/testrunner/tests/testrunner-knit.rst
zope/testrunner/tests/testrunner-layers-api.rst
zope/testrunner/tests/testrunner-layers-buff.rst
zope_testrunner-8.1.dist-info/LICENSE.md
zope_testrunner-8.1.dist-info/METADATA
zope_testrunner-8.1.dist-info/WHEEL
zope_testrunner-8.1.dist-info/entry_points.txt
zope_testrunner-8.1.dist-info/top_level.txt
zope_testrunner-8.1.dist-info/RECORD
